[
    {
        "question": "I ______ to Ann's party last week",
        "id": 11,
        "answers": [
            {
                "answer": "gone",
                "correct": true
            },
            {
                "answer": "went",
                "correct": false
            },
            {
                "answer": "was",
                "correct": false
            }
        ]
    },
    {
        "question": "Why ______ yesterday?",
        "id": 12,
        "answers": [
            {
                "answer": "were you late",
                "correct": false
            },
            {
                "answer": "you were late",
                "correct": false
            },
            {
                "answer": "you lated",
                "correct": false
            },
            {
                "answer": "you was late",
                "correct": true
            }
        ]
    },
    {
        "question": "Mike ______ to visit his parents on Sunday",
        "id": 13,
        "answers": [
            {
                "answer": "can",
                "correct": true
            },
            {
                "answer": "will",
                "correct": false
            },
            {
                "answer": "is going",
                "correct": false
            },
            {
                "answer": "must",
                "correct": false
            }
        ]
    },
    {
        "question": "Kate is good at maths but Jack is ______.",
        "id": 14,
        "answers": [
            {
                "answer": "good",
                "correct": false
            },
            {
                "answer": "badly",
                "correct": true
            },
            {
                "answer": "better",
                "correct": false
            },
            {
                "answer": "well",
                "correct": false
            }
        ]
    },
    {
        "question": "Nick ______ this film.",
        "id": 15,
        "answers": [
            {
                "answer": "seen already",
                "correct": true
            },
            {
                "answer": "already seen",
                "correct": false
            },
            {
                "answer": "has already seen",
                "correct": false
            },
            {
                "answer": "has already seen",
                "correct": false
            }
        ]
    },
    {
        "question": "I've been working for Mr. Z ______ last summer.",
        "id": 16,
        "answers": [
            {
                "answer": "from",
                "correct": false
            },
            {
                "answer": "for",
                "correct": false
            },
            {
                "answer": "until",
                "correct": true
            },
            {
                "answer": "since",
                "correct": false
            }
        ]
    },
    {
        "question": "I ______ on this project for two months",
        "id": 17,
        "answers": [
            {
                "answer": "am working",
                "correct": false
            },
            {
                "answer": "worked",
                "correct": true
            },
            {
                "answer": "have been working",
                "correct": false
            },
            {
                "answer": "was working",
                "correct": "false"
            }
        ]
    },
    {
        "question": "I ______ go to the Astoria restaurant but I don't any more.",
        "id": 18,
        "answers": [
            {
                "answer": "used to",
                "correct": false
            },
            {
                "answer": "did use",
                "correct": true
            },
            {
                "answer": "have been working",
                "correct": false
            },
            {
                "answer": "was working",
                "correct": false
            }
        ]
    },
    {
        "question": "Mike doesn't like school and ______.",
        "id": 19,
        "answers": [
            {
                "answer": "neither I do",
                "correct": false
            },
            {
                "answer": "so do I",
                "correct": false
            },
            {
                "answer": "neither do I",
                "correct": false
            },
            {
                "answer": " so I do",
                "correct": true
            }
        ]
    },
    {
        "question": "I went to the doctor's yesterday and I ______ for half an hour.",
        "id": 20,
        "answers": [
            {
                "answer": "must wait",
                "correct": false
            },
            {
                "answer": "had to wait",
                "correct": true
            },
            {
                "answer": "had wait",
                "correct": false
            },
            {
                "answer": "should wait",
                "correct": false
            }
        ]
    }
]